prezzemolo/__init__.py
prezzemolo/avl_tree.py
prezzemolo/graph.py
prezzemolo/py.typed
prezzemolo/utility.py
prezzemolo/vertex.py
prezzemolo-0.0.4.dist-info/LICENSE
prezzemolo-0.0.4.dist-info/METADATA
prezzemolo-0.0.4.dist-info/WHEEL
prezzemolo-0.0.4.dist-info/top_level.txt
prezzemolo-0.0.4.dist-info/RECORD
