Metadata-Version: 2.1
Name: prezzemolo
Version: 0.0.4
Summary: A collection of robust, efficient and small classic algorithms and data structures.
Home-page: https://github.com/eprbell/prezzemolo
Author: eprbell
License: Apache License 2.0
Project-URL: Source Code, https://github.com/eprbell/prezzemolo
Project-URL: Developer Documentation, https://github.com/eprbell/prezzemolo/blob/main/README.dev.md
Project-URL: User Documentation, https://github.com/eprbell/prezzemolo/blob/main/README.md
Project-URL: Contact, https://eprbell.github.io/eprbell/about.html
Keywords: utility,algorithm,data structure,tree,graph
Classifier: Development Status :: 4 - Beta
Classifier: Intended Audience :: End Users/Desktop
Classifier: License :: OSI Approved :: Apache Software License
Classifier: Operating System :: OS Independent
Classifier: Programming Language :: Python :: 3.7
Classifier: Programming Language :: Python :: 3.8
Classifier: Programming Language :: Python :: 3.9
Classifier: Programming Language :: Python :: 3.10
Classifier: Topic :: Software Development :: Libraries
Classifier: Topic :: Software Development :: Libraries :: Python Modules
Classifier: Topic :: Utilities
Classifier: Typing :: Typed
License-File: LICENSE
Provides-Extra: dev
Requires-Dist: autopep8 ; extra == 'dev'
Requires-Dist: bandit ; extra == 'dev'
Requires-Dist: black ; extra == 'dev'
Requires-Dist: bumpversion ; extra == 'dev'
Requires-Dist: flake8 ; extra == 'dev'
Requires-Dist: isort ; extra == 'dev'
Requires-Dist: mypy ; extra == 'dev'
Requires-Dist: pep8 ; extra == 'dev'
Requires-Dist: pre-commit ; extra == 'dev'
Requires-Dist: pylint ; extra == 'dev'
Requires-Dist: pytest ; extra == 'dev'
Requires-Dist: pytest-mock ; extra == 'dev'
Requires-Dist: rope ; extra == 'dev'
